[{"info1": "Wir fahren um zw\u00f6lf Uhr ab.", "info2": "", "date": "2018-12-29 21:09:25.179255", "chunk": 0, "question": "\ufeffabfahren ", "difficulty": 1, "answer": "\ucd9c\ubc1c\ud558\ub2e4\n", "learned": false}, {"info1": "Ich muss meine Schl\u00fcssel abgeben.", "info2": "", "date": "2018-12-29 21:09:25.179255", "chunk": 0, "question": "abgeben ", "difficulty": 1, "answer": "\uc81c\ucd9c\ud558\ub2e4\n", "learned": false}, {"info1": "Wann kann ich den Schrank bei dir abholen?", "info2": "", "date": "2018-12-29 21:09:25.179255", "chunk": 0, "question": "abholen ", "difficulty": 1, "answer": "\ubc1b\ub2e4\n", "learned": false}, {"info1": "Was darf ich dir anbieten?", "info2": "", "date": "2018-12-29 21:09:25.179255", "chunk": 0, "question": "anbieten ", "difficulty": 1, "answer": "\uc81c\uc548\ud558\ub2e4\n", "learned": false}, {"info1": "Hier f\u00e4ngt die Bahnhofstra\u00dfe an.", "info2": "", "date": "2018-12-29 21:09:25.179255", "chunk": 0, "question": "anfangen ", "difficulty": 1, "answer": "\uc2dc\uc791\ud558\ub2e4\n", "learned": false}, {"info1": "Da musst du dieses Wort anklicken.", "info2": "", "date": "2018-12-29 21:09:25.179255", "chunk": 0, "question": "anklicken ", "difficulty": 1, "answer": "\ud074\ub9ad\ud558\ub2e4\n", "learned": false}, {"info1": "Wann kommt dieser Zug in Hamburg an?", "info2": "", "date": "2018-12-29 21:09:25.179255", "chunk": 0, "question": "ankommen ", "difficulty": 1, "answer": "\ub3c4\ucc29\ud558\ub2e4\n", "learned": false}, {"info1": "Mach bitte das Licht an!", "info2": "", "date": "2018-12-29 21:09:25.179255", "chunk": 0, "question": "anmachen ", "difficulty": 1, "answer": "\ud0a4\ub2e4\n", "learned": false}, {"info1": "Kann man Sie anrufen?", "info2": "", "date": "2018-12-29 21:09:25.179255", "chunk": 0, "question": "anrufen ", "difficulty": 1, "answer": "\uc804\ud654\ud558\ub2e4\n", "learned": false}, {"info1": "Er antwortet nicht.", "info2": "", "date": "2018-12-29 21:09:25.179255", "chunk": 0, "question": "antworten ", "difficulty": 1, "answer": "\ub300\ub2f5\ud558\ub2e4\n", "learned": false}, {"info1": "Wo arbeiten Sie?", "info2": "", "date": "2018-12-29 21:09:25.179255", "chunk": 1, "question": "arbeiten ", "difficulty": 1, "answer": "\uc77c\ud558\ub2e4, \ub178\ub3d9\ud558\ub2e4\n", "learned": false}, {"info1": "Du brauchst den Schl\u00fcssel nicht. Die Wohnung ist auf.", "info2": "", "date": "2018-12-29 21:09:25.179255", "chunk": 1, "question": "auf sein ", "difficulty": 1, "answer": "\uc5f4\uc5b4\ub193\uace0\u00a0\uc788\ub2e4, \uc5f4\uc5b4\ub450\uace0 \uc788\ub2e4\n", "learned": false}, {"info1": "Der Kurs h\u00f6rt in einer Woche auf.", "info2": "", "date": "2018-12-29 21:09:25.179255", "chunk": 1, "question": "aufh\u00f6ren ", "difficulty": 1, "answer": "\ub05d\ub098\ub2e4\n", "learned": false}, {"info1": "Ich muss immer um vier Uhr aufstehen.", "info2": "", "date": "2018-12-29 21:09:25.179255", "chunk": 1, "question": "aufstehen ", "difficulty": 1, "answer": "\uc77c\uc5b4\ub098\ub2e4\n", "learned": false}, {"info1": "F\u00fcllen Sie bitte dieses Formular aus.", "info2": "", "date": "2018-12-29 21:09:25.179255", "chunk": 1, "question": "ausf\u00fcllen ", "difficulty": 1, "answer": "\uc791\uc131\ud558\ub2e4\n", "learned": false}, {"info1": "Das Licht ist aus.", "info2": "", "date": "2018-12-29 21:09:25.179255", "chunk": 1, "question": "aus sein", "difficulty": 1, "answer": "\uaebc\uc84c\ub2e4\n", "learned": false}, {"info1": "Mach bitte das Licht aus!", "info2": "", "date": "2018-12-29 21:09:25.179255", "chunk": 1, "question": "ausmachen ", "difficulty": 1, "answer": "\ub044\ub2e4\n", "learned": false}, {"info1": "Das sieht sch\u00f6n aus.", "info2": "", "date": "2018-12-29 21:09:25.179255", "chunk": 1, "question": "aussehen ", "difficulty": 1, "answer": "\ubcf4\uc774\ub2e4\n", "learned": false}, {"info1": "Wo muss ich aussteigen?", "info2": "", "date": "2018-12-29 21:09:25.179255", "chunk": 1, "question": "aussteigen ", "difficulty": 1, "answer": "\ub5a0\ub098\ub2e4\n", "learned": false}, {"info1": "Ich bade nicht so gern, ich dusche lieber.", "info2": "", "date": "2018-12-29 21:09:25.179255", "chunk": 1, "question": "baden ", "difficulty": 1, "answer": "\ubaa9\uc695\uc2dc\ud0a4\ub2e4, \ubaa9\uc695\uc744 \ud558\ub2e4\n", "learned": false}, {"info1": "Was bedeutet das Wort?", "info2": "", "date": "2018-12-29 21:09:25.179255", "chunk": 2, "question": "bedeuten ", "difficulty": 1, "answer": "\ub73b\ud558\ub2e4, \uc758\ubbf8\ud558\ub2e4\n", "learned": false}, {"info1": "Das Spiel beginnt um 15.30 Uhr.", "info2": "", "date": "2018-12-29 21:09:25.179255", "chunk": 2, "question": "beginnen ", "difficulty": 1, "answer": "\uc2dc\uc791\ud558\ub2e4, \ucc29\uc218\ud558\ub2e4\n", "learned": false}, {"info1": "Haben Sie meinen Brief bekommen?", "info2": "", "date": "2018-12-29 21:09:25.180221", "chunk": 2, "question": "bekommen ", "difficulty": 1, "answer": "\uc5bb\ub2e4, \ubc1b\ub2e4, \ud68d\ub4dd\ud558\ub2e4\n", "learned": false}, {"info1": "Die Aufz\u00fcge bitte nicht benutzen!", "info2": "", "date": "2018-12-29 21:09:25.180221", "chunk": 2, "question": "benutzen ", "difficulty": 1, "answer": "\uc774\uc6a9\ud558\ub2e4, \uc0ac\uc6a9\ud558\ub2e4\n", "learned": false}, {"info1": "Die Nummer ist immer besetzt.", "info2": "", "date": "2018-12-29 21:09:25.180221", "chunk": 2, "question": "besetzt ", "difficulty": 1, "answer": "\uc810\ub839,  \uc810\ub839\ud558\ub2e4\n", "learned": false}, {"info1": "Ich m\u00f6chte gern den Dom besichtigen.", "info2": "", "date": "2018-12-29 21:09:25.180221", "chunk": 2, "question": "besichtigen ", "difficulty": 1, "answer": "\ubc29\ubb38\ud558\ub2e4, \uad00\ub78c\ud558\ub2e4, \uc2dc\ucc30\ud558\ub2e4\n", "learned": false}, {"info1": "Wir m\u00f6chten bestellen, bitte.", "info2": "", "date": "2018-12-29 21:09:25.180221", "chunk": 2, "question": "bestellen ", "difficulty": 1, "answer": "\uc8fc\ubb38\ud558\ub2e4\n", "learned": false}, {"info1": "Darf ich dich besuchen?", "info2": "", "date": "2018-12-29 21:09:25.180221", "chunk": 2, "question": "besuchen ", "difficulty": 1, "answer": "\ubc29\ubb38\ud558\ub2e4, \ubb38\uc548\uac00\ub2e4\n", "learned": false}, {"info1": "Wo muss ich bezahlen?", "info2": "", "date": "2018-12-29 21:09:25.180221", "chunk": 2, "question": "bezahlen ", "difficulty": 1, "answer": "\uc9c0\uae09\ud558\ub2e4, \uac1a\ub2e4\n", "learned": false}, {"info1": "Darf ich Sie um etwas bitten?", "info2": "", "date": "2018-12-29 21:09:25.180221", "chunk": 2, "question": "bitten ", "difficulty": 1, "answer": "\ubd80\ud0c1\ud558\ub2e4\n", "learned": false}, {"info1": "Ich bleibe heute zu Hause.", "info2": "", "date": "2018-12-29 21:09:25.180221", "chunk": 3, "question": "bleiben ", "difficulty": 1, "answer": "\uba38\ubb34\ub974\ub2e4, \ub0a8\ub2e4\n", "learned": false}, {"info1": "Brauchst du die Zeitung noch?", "info2": "", "date": "2018-12-29 21:09:25.180221", "chunk": 3, "question": "brauchen ", "difficulty": 1, "answer": "\ud544\uc694\ud558\ub2e4\n", "learned": false}, {"info1": "Bringen Sie mir bitte noch einen Kaffee!", "info2": "", "date": "2018-12-29 21:09:25.180221", "chunk": 3, "question": "bringen ", "difficulty": 1, "answer": "\ubcf4\ub0b4\ub2e4\n", "learned": false}, {"info1": "Bitte buchstabieren Sie Ihren Namen.", "info2": "", "date": "2018-12-29 21:09:25.180221", "chunk": 3, "question": "buchstabieren ", "difficulty": 1, "answer": "\ud55c\uc790\ud55c\uc790 \uc77d\ub2e4/\ub9d0\ud558\ub2e4\n", "learned": false}, {"info1": "Ich danke Ihnen f\u00fcr die Einladung.", "info2": "", "date": "2018-12-29 21:09:25.180221", "chunk": 3, "question": "danken ", "difficulty": 1, "answer": "\uac10\uc0ac\ud558\ub2e4\n", "learned": false}, {"info1": "Wie lange dauert der Film?", "info2": "", "date": "2018-12-29 21:09:25.180221", "chunk": 3, "question": "dauern ", "difficulty": 1, "answer": "(\uc2dc\uac04) \uac78\ub9ac\ub2e4\n", "learned": false}, {"info1": "Bitte drucke das Formular f\u00fcr mich.", "info2": "", "date": "2018-12-29 21:09:25.180221", "chunk": 3, "question": "drucken ", "difficulty": 1, "answer": "\ud504\ub9b0\ud2b8\ub97c \ud558\ub2e4\n", "learned": false}, {"info1": "Dr\u00fcck hier, dann geht der Computer an.", "info2": "", "date": "2018-12-29 21:09:25.180221", "chunk": 3, "question": "dr\u00fccken ", "difficulty": 1, "answer": "\ub204\ub974\ub2e4, \ubc00\ub2e4\n", "learned": false}, {"info1": "Sie d\u00fcrfen hier nicht rauchen.", "info2": "", "date": "2018-12-29 21:09:25.180221", "chunk": 3, "question": "d\u00fcrfen ", "difficulty": 1, "answer": "~\uba74\ub41c\ub2e4, ~\ub3c4\ub41c\ub2e4\n", "learned": false}, {"info1": "Ich bade nicht so gern, ich dusche lieber.", "info2": "", "date": "2018-12-29 21:09:25.180221", "chunk": 3, "question": "duschen ", "difficulty": 1, "answer": "\uc0e4\uc6cc\ub97c \ud558\ub2e4.\n", "learned": false}, {"info1": "Ich muss noch f\u00fcr morgen einkaufen.", "info2": "", "date": "2018-12-29 21:09:25.180221", "chunk": 4, "question": "einkaufen ", "difficulty": 1, "answer": "\uc7a5\ubcf4\ub7ec \uac00\ub2e4\n", "learned": false}, {"info1": "Darf ich Sie zu einem Kaffee einladen?", "info2": "", "date": "2018-12-29 21:09:25.180221", "chunk": 4, "question": "einladen ", "difficulty": 1, "answer": "\ucd08\ub300\ud558\ub2e4\n", "learned": false}, {"info1": "Schnell, steig ein, der Zug f\u00e4hrt gleich.", "info2": "", "date": "2018-12-29 21:09:25.180221", "chunk": 4, "question": "einsteigen ", "difficulty": 1, "answer": "\uc62c\ub77c\ud0c0\ub2e4\n", "learned": false}, {"info1": "Welchen Wein k\u00f6nnen Sie mir empfehlen?", "info2": "", "date": "2018-12-29 21:09:25.180221", "chunk": 4, "question": "empfehlen ", "difficulty": 1, "answer": "\ucd94\ucc9c\ud558\ub2e4\n", "learned": false}, {"info1": "Die Stra\u00dfe endet hier.", "info2": "", "date": "2018-12-29 21:09:25.180221", "chunk": 4, "question": "enden ", "difficulty": 1, "answer": "\ub05d\ub0b4\ub2e4, \ub2e4\ud558\ub2e4\n", "learned": false}, {"info1": "Entschuldigen Sie bitte!", "info2": "", "date": "2018-12-29 21:09:25.180221", "chunk": 4, "question": "entschuldigen ", "difficulty": 1, "answer": "\uc6a9\uc11c\ud558\ub2e4\n", "learned": false}, {"info1": "Kannst du mir das erkl\u00e4ren?", "info2": "", "date": "2018-12-29 21:09:25.180221", "chunk": 4, "question": "erkl\u00e4ren ", "difficulty": 1, "answer": "\uc124\uba85\ud558\ub2e4, \ud574\uba85\ud558\ub2e4\n", "learned": false}, {"info1": "Rauchen ist hier nicht erlaubt.", "info2": "", "date": "2018-12-29 21:09:25.180221", "chunk": 4, "question": "erlauben ", "difficulty": 1, "answer": "\ud5c8\ub77d\ud558\ub2e4,\ud5c8\uac00\ud558\ub2e4, \ub3d9\uc758\ud558\ub2e4\n", "learned": false}, {"info1": "Wir m\u00fcssen euch etwas erz\u00e4hlen!", "info2": "", "date": "2018-12-29 21:09:25.180221", "chunk": 4, "question": "erz\u00e4hlen ", "difficulty": 1, "answer": "\ud558\ub098\uc529 \ud558\ub098\uc529 \uc138\uc5b4 \ub098\uac00\ub2e4.\n", "learned": false}, {"info1": "Ich fahre mit dem Auto zur Arbeit.", "info2": "", "date": "2018-12-29 21:09:25.180221", "chunk": 4, "question": "fahren ", "difficulty": 1, "answer": "\ud0c0\ub2e4\n", "learned": false}, {"info1": "Wir feiern heute meinen Geburtstag.", "info2": "", "date": "2018-12-29 21:09:25.180221", "chunk": 5, "question": "feiern ", "difficulty": 1, "answer": "\ub180\ub2e4, \uc77c\uc744 \uc26c\ub2e4, \ud734\uc5c5\ud558\ub2e4\n", "learned": false}, {"info1": "Herr M\u00fcller ist nicht da, er fehlt schon seit drei Tagen.", "info2": "", "date": "2018-12-29 21:09:25.180221", "chunk": 5, "question": "fehlen ", "difficulty": 1, "answer": "\uc5c6\ub2e4, \uc5c6\uc5b4\uc84c\ub2e4\n", "learned": false}, {"info1": "Wollen wir heute Abend mal fernsehen?", "info2": "", "date": "2018-12-29 21:09:25.180221", "chunk": 5, "question": "fernsehen ", "difficulty": 1, "answer": "\ud154\ub808\ube44\uc804\uc744 \ubcf4\ub2e4\n", "learned": false}, {"info1": "Wir m\u00fcssen den Schl\u00fcssel finden.", "info2": "", "date": "2018-12-29 21:09:25.180221", "chunk": 5, "question": "finden ", "difficulty": 1, "answer": "\ubc1c\uacac\ud558\ub2e4, \ucc3e\uc544\ub0b4\ub2e4\n", "learned": false}, {"info1": "Ich fliege nicht gern. Deshalb fahre ich mit dem Zug.", "info2": "", "date": "2018-12-29 21:09:25.180221", "chunk": 5, "question": "fliegen ", "difficulty": 1, "answer": "\ub0a0\ub2e4, \ube44\ud589\uae30\ub85c \uac00\ub2e4\n", "learned": false}, {"info1": "Wann fliegst du ab?", "info2": "", "date": "2018-12-29 21:09:25.180221", "chunk": 5, "question": "abfliegen ", "difficulty": 1, "answer": "\uc774\ub959\ud558\ub2e4\n", "learned": false}, {"info1": "Er m\u00f6chte Sie etwas fragen. Wann kommen Sie?", "info2": "", "date": "2018-12-29 21:09:25.180221", "chunk": 5, "question": "fragen ", "difficulty": 1, "answer": "\ubb3b\ub2e4, \uc9c8\ubb38\ud558\ub2e4\n", "learned": false}, {"info1": "Am Sonntag fr\u00fchst\u00fccke ich gern im Bett.", "info2": "", "date": "2018-12-29 21:09:25.180221", "chunk": 5, "question": "fr\u00fchst\u00fccken ", "difficulty": 1, "answer": "\uc544\uce68 \uc2dd\uc0ac\ub97c \ud558\ub2e4\n", "learned": false}, {"info1": "Kannst du mir bitte deinen Kugelschreiber geben?", "info2": "", "date": "2018-12-29 21:09:25.180221", "chunk": 5, "question": "geben ", "difficulty": 1, "answer": "\uc8fc\ub2e4\n", "learned": false}, {"info1": "Das gef\u00e4llt mir.", "info2": "", "date": "2018-12-29 21:09:25.180221", "chunk": 5, "question": "gefallen ", "difficulty": 1, "answer": "\ub9c8\uc74c\uc5d0 \ub4e0\ub2e4\n", "learned": false}, {"info1": "Ich muss zum Arzt gehen.", "info2": "", "date": "2018-12-29 21:09:25.180221", "chunk": 6, "question": "gehen ", "difficulty": 1, "answer": "\uac00\ub2e4\n", "learned": false}, {"info1": "Wem geh\u00f6rt das?", "info2": "", "date": "2018-12-29 21:09:25.180221", "chunk": 6, "question": "geh\u00f6ren ", "difficulty": 1, "answer": "\uc18c\uc720\ud558\ub2e4\n", "learned": false}, {"info1": "Wer gewinnt das Spiel?", "info2": "", "date": "2018-12-29 21:09:25.180221", "chunk": 6, "question": "gewinnen ", "difficulty": 1, "answer": "\uc774\uae30\ub2e4\n", "learned": false}, {"info1": "Sie k\u00f6nnen mir glauben, es ist so.", "info2": "", "date": "2018-12-29 21:09:25.180221", "chunk": 6, "question": "glauben ", "difficulty": 1, "answer": "\ubbff\ub2e4\n", "learned": false}, {"info1": "Ich gratuliere dir!", "info2": "", "date": "2018-12-29 21:09:25.180221", "chunk": 6, "question": "gratulieren ", "difficulty": 1, "answer": "\ucd95\ud558\ud558\ub2e4\n", "learned": false}, {"info1": "Heute grillen wir im Garten.", "info2": "", "date": "2018-12-29 21:09:25.180221", "chunk": 6, "question": "grillen ", "difficulty": 1, "answer": "\uad7d\ub2e4\n", "learned": false}, {"info1": "Ich habe ein neues Auto.", "info2": "", "date": "2018-12-29 21:09:25.180221", "chunk": 6, "question": "haben ", "difficulty": 1, "answer": "\ubb34\uc5c7\uc744 \uac00\uc9c0\uace0 \uc788\ub2e4\n", "learned": false}, {"info1": "Dieser Zug h\u00e4lt nicht in R\u00fcdesheim.", "info2": "", "date": "2018-12-29 21:09:25.180221", "chunk": 6, "question": "halten ", "difficulty": 1, "answer": "\uba48\ucd94\ub2e4, \uc7a1\ub2e4\n", "learned": false}, {"info1": "Meine Schwester heiratet einen Japaner.", "info2": "", "date": "2018-12-29 21:09:25.180221", "chunk": 6, "question": "heiraten ", "difficulty": 1, "answer": "\uacb0\ud63c\ud558\ub2e4\n", "learned": false}, {"info1": "Wie hei\u00dft das auf Deutsch?", "info2": "", "date": "2018-12-29 21:09:25.181218", "chunk": 6, "question": "hei\u00dfen ", "difficulty": 1, "answer": "\uc774\ub77c\uace0 \ubd80\ub974\ub2e4, \uc77c\uceeb\ub2e4, \uc774\ub984 \ubd99\uc774\ub2e4\n", "learned": false}, {"info1": "K\u00f6nnen Sie mir helfen, bitte?", "info2": "", "date": "2018-12-29 21:09:25.181218", "chunk": 7, "question": "helfen ", "difficulty": 1, "answer": "\ub204\uad6c\ub97c \ub3d5\ub2e4\n", "learned": false}, {"info1": "Ich hole zwei Flaschen Wasser aus der K\u00fcche.", "info2": "", "date": "2018-12-29 21:09:25.181218", "chunk": 7, "question": "holen ", "difficulty": 1, "answer": "\uac00\uc838\uc624\ub2e4\n", "learned": false}, {"info1": "Tim kauft sich ein neues Auto.", "info2": "", "date": "2018-12-29 21:09:25.181218", "chunk": 7, "question": "kaufen ", "difficulty": 1, "answer": "\uc0ac\ub2e4, \uad6c\uc785\ud558\ub2e4\n", "learned": false}, {"info1": "Kennen Sie diese Frau? \u2013 Nein, leider nicht.", "info2": "", "date": "2018-12-29 21:09:25.181218", "chunk": 7, "question": "kennen ", "difficulty": 1, "answer": "\uc54c(\uace0 \uc788) \ub2e4, \uc778\uc9c0\ud558\ub2e4\n", "learned": false}, {"info1": "Wir sind neu hier. Wir m\u00f6chten Sie kennenlernen.", "info2": "", "date": "2018-12-29 21:09:25.181218", "chunk": 7, "question": "kennenlernen ", "difficulty": 1, "answer": "\uc544\ub294 \uc0ac\uc774\uac00 \ub418\ub2e4\n", "learned": false}, {"info1": "Herr Georgi kann gut kochen.", "info2": "", "date": "2018-12-29 21:09:25.181218", "chunk": 7, "question": "kochen ", "difficulty": 1, "answer": "\uc694\ub9ac\ud558\ub2e4\n", "learned": false}, {"info1": "Woher kommen Sie? \u2013 Aus Frankreich.", "info2": "", "date": "2018-12-29 21:09:25.181218", "chunk": 7, "question": "kommen ", "difficulty": 1, "answer": "\uc624\ub2e4\n", "learned": false}, {"info1": "Ich kann Deutsch und Russisch.", "info2": "", "date": "2018-12-29 21:09:25.181218", "chunk": 7, "question": "k\u00f6nnen ", "difficulty": 1, "answer": "\ud560 \uc904 \uc54c\ub2e4, \ud560 \uc218 \uc788\ub2e4\n", "learned": false}, {"info1": "Wie viel kostet das? \u2013 10 Euro.", "info2": "", "date": "2018-12-29 21:09:25.181218", "chunk": 7, "question": "kosten ", "difficulty": 1, "answer": "\ub9db\ubcf4\ub2e4, xxx\uc6d0\uc785\ub2c8\ub2e4\n", "learned": false}, {"info1": "Ich kriege 15 Euro in der Stunde f\u00fcr meine Arbeit.", "info2": "", "date": "2018-12-29 21:09:25.181218", "chunk": 7, "question": "kriegen ", "difficulty": 1, "answer": "\uc5bb\ub2e4, \ubc1b\ub2e4\n", "learned": false}, {"info1": "Jede Mutter k\u00fcmmert sich um ihre kleinen Kinder.", "info2": "", "date": "2018-12-29 21:09:25.181218", "chunk": 8, "question": "sich k\u00fcmmern", "difficulty": 1, "answer": "\ub3cc\ubcf4\ub2e4\n", "learned": false}, {"info1": "Die Kinder lachen viel.", "info2": "", "date": "2018-12-29 21:09:25.181218", "chunk": 8, "question": "lachen ", "difficulty": 1, "answer": "\uc6c3\ub2e4\n", "learned": false}, {"info1": "Ich m\u00f6chte nicht Auto fahren, ich m\u00f6chte laufen.", "info2": "", "date": "2018-12-29 21:09:25.181218", "chunk": 8, "question": "laufen ", "difficulty": 1, "answer": "\ub2ec\ub9ac\ub2e4, \ub6f0\ub2e4\n", "learned": false}, {"info1": "Sie lebt bei ihrer Schwester.", "info2": "", "date": "2018-12-29 21:09:25.181218", "chunk": 8, "question": "leben ", "difficulty": 1, "answer": "\uc0b4\ub2e4\n", "learned": false}, {"info1": "Legen Sie das Buch auf den Tisch.", "info2": "", "date": "2018-12-29 21:09:25.181218", "chunk": 8, "question": "legen ", "difficulty": 1, "answer": "\ub450\ub2e4, \ub193\ub2e4\n", "learned": false}, {"info1": "Wie lange lernen Sie schon Deutsch?", "info2": "", "date": "2018-12-29 21:09:25.181218", "chunk": 8, "question": "lernen ", "difficulty": 1, "answer": "\ubc30\uc6b0\ub2e4, \uacf5\ubd80\ud558\ub2e4\n", "learned": false}, {"info1": "Ich lese ein Buch von Garc\u00eda M\u00e1rquez.", "info2": "", "date": "2018-12-29 21:09:25.181218", "chunk": 8, "question": "lesen ", "difficulty": 1, "answer": "\uc77d\ub2e4\n", "learned": false}, {"info1": "Ich liebe dich!", "info2": "", "date": "2018-12-29 21:09:25.181218", "chunk": 8, "question": "lieben ", "difficulty": 1, "answer": "\uc0ac\ub791\ud558\ub2e4\n", "learned": false}, {"info1": "Um neun Uhr liegt Judith noch im Bett.", "info2": "", "date": "2018-12-29 21:09:25.181218", "chunk": 8, "question": "liegen ", "difficulty": 1, "answer": "\ub204\uc6cc \uc788\ub2e4, \ub193\uc5ec \uc788\ub2e4\n", "learned": false}, {"info1": "Was machst du heute Abend?", "info2": "", "date": "2018-12-29 21:09:25.181218", "chunk": 8, "question": "machen ", "difficulty": 1, "answer": "\ud558\ub2e4, \ub9cc\ub4e4\ub2e4\n", "learned": false}, {"info1": "Ich m\u00f6chte ein Auto mieten.", "info2": "", "date": "2018-12-29 21:09:25.181218", "chunk": 9, "question": "mieten ", "difficulty": 1, "answer": "\uc784\ucc28\ud558\ub2e4, \ube4c\ub9ac\ub2e4\n", "learned": false}, {"info1": "Ich gehe einkaufen. Soll ich dir was mitbringen?", "info2": "", "date": "2018-12-29 21:09:25.181218", "chunk": 9, "question": "mitbringen ", "difficulty": 1, "answer": "\uac00\uc9c0\uace0 \uac00\ub2e4\n", "learned": false}, {"info1": "Ich gehe ins Kino. Kommst du mit?", "info2": "", "date": "2018-12-29 21:09:25.181218", "chunk": 9, "question": "mitkommen ", "difficulty": 1, "answer": "\uac19\uc774 \uac00\ub2e4\n", "learned": false}, {"info1": "Warum macht ihr nicht mit?", "info2": "", "date": "2018-12-29 21:09:25.181218", "chunk": 9, "question": "mitmachen ", "difficulty": 1, "answer": "\ucc38\uac00\ud558\ub2e4, \ucc38\uc5ec\ud558\ub2e4\n", "learned": false}, {"info1": "Nehmen wir meine Schwester ins Kino mit?", "info2": "", "date": "2018-12-29 21:09:25.181218", "chunk": 9, "question": "mitnehmen ", "difficulty": 1, "answer": "\ub370\ub9ac\uace0 \uac00\ub2e4\n", "learned": false}, {"info1": "Was m\u00f6chten Sie trinken?", "info2": "", "date": "2018-12-29 21:09:25.181218", "chunk": 9, "question": "m\u00f6chten ", "difficulty": 1, "answer": "\uc6d0\ud558\ub2e4\n", "learned": false}, {"info1": "Magst du Kaffee oder Tee?", "info2": "", "date": "2018-12-29 21:09:25.181218", "chunk": 9, "question": "m\u00f6gen ", "difficulty": 1, "answer": "\uc88b\uc544\ud558\ub2e4\n", "learned": false}, {"info1": "Ich muss jeden Tag von 8 Uhr bis 18 Uhr arbeiten.", "info2": "", "date": "2018-12-29 21:09:25.181218", "chunk": 9, "question": "m\u00fcssen ", "difficulty": 1, "answer": "\u2219\u2219\u2219\ud558\uc9c0 \uc54a\uc73c\uba74 \uc548\ub418\ub2e4, \u2219\u2219\u2219\ud574\uc57c \ud55c\ub2e4\n", "learned": false}, {"info1": "Heute gibt es H\u00e4hnchen. Das nehme ich.", "info2": "", "date": "2018-12-29 21:09:25.181218", "chunk": 9, "question": "nehmen ", "difficulty": 1, "answer": "\uac00\uc838\uac00\ub2e4\n", "learned": false}, {"info1": "Ich \u00f6ffne die T\u00fcr.", "info2": "", "date": "2018-12-29 21:09:25.181218", "chunk": 9, "question": "\u00f6ffnen ", "difficulty": 1, "answer": "\uc5f4\ub2e4\n", "learned": false}, {"info1": "Das Kind kann schon Rad fahren.", "info2": "", "date": "2018-12-29 21:09:25.181218", "chunk": 10, "question": "Rad fahren", "difficulty": 1, "answer": "\uc790\uc804\uac70\ub97c \ud0c0\ub2e4\n", "learned": false}, {"info1": "Ich rauche nicht.", "info2": "", "date": "2018-12-29 21:09:25.181218", "chunk": 10, "question": "rauchen ", "difficulty": 1, "answer": "\ub2f4\ubc30\ub97c \ud53c\uc6b0\ub2e4\n", "learned": false}, {"info1": "Heute regnet es.", "info2": "", "date": "2018-12-29 21:09:25.181218", "chunk": 10, "question": "regnen ", "difficulty": 1, "answer": "\ube44\uac00 \uc628\ub2e4\n", "learned": false}, {"info1": "Ich reise gern.", "info2": "", "date": "2018-12-29 21:09:25.181218", "chunk": 10, "question": "reisen ", "difficulty": 1, "answer": "\uc5ec\ud589\ud558\ub2e4, \uc5ec\ud589\uc744 \ub5a0\ub098\ub2e4\n", "learned": false}, {"info1": "Er hat das Fahrrad repariert.", "info2": "", "date": "2018-12-29 21:09:25.181218", "chunk": 10, "question": "reparieren ", "difficulty": 1, "answer": "\uc218\ub9ac\ud558\ub2e4\n", "learned": false}, {"info1": "Dieser Wein riecht gut.", "info2": "", "date": "2018-12-29 21:09:25.181218", "chunk": 10, "question": "riechen ", "difficulty": 1, "answer": "\ub0c4\uc0c8\ub97c \ud48d\uae30\ub2e4, \ub0c4\uc0c8\uac00 \ub098\ub2e4\n", "learned": false}, {"info1": "Sag mal, wie geht es dir denn?", "info2": "", "date": "2018-12-29 21:09:25.181218", "chunk": 10, "question": "sagen ", "difficulty": 1, "answer": "\ub9d0\ud558\ub2e4\n", "learned": false}, {"info1": "Die Sonne scheint.", "info2": "", "date": "2018-12-29 21:09:25.181218", "chunk": 10, "question": "scheinen ", "difficulty": 1, "answer": "\ube5b\ub098\ub2e4\n", "learned": false}, {"info1": "Bitte schicken Sie mir eine E-Mail.", "info2": "", "date": "2018-12-29 21:09:25.181218", "chunk": 10, "question": "schicken ", "difficulty": 1, "answer": "\ubcf4\ub0b4\ub2e4, \ubd80\uce58\ub2e4\n", "learned": false}, {"info1": "Ich schlafe meistens acht Stunden.", "info2": "", "date": "2018-12-29 21:09:25.181218", "chunk": 10, "question": "schlafen ", "difficulty": 1, "answer": "\uc790\ub2e4, \uc7a0\uc790\ub2e4, \uc26c\uace0 \uc788\ub2e4\n", "learned": false}, {"info1": "Bitte, schlie\u00dfen Sie die T\u00fcr.", "info2": "", "date": "2018-12-29 21:09:25.181218", "chunk": 11, "question": "schlie\u00dfen ", "difficulty": 1, "answer": "\ub2eb\ub2e4\n", "learned": false}, {"info1": "Schmeckt das gut?", "info2": "", "date": "2018-12-29 21:09:25.181218", "chunk": 11, "question": "schmecken ", "difficulty": 1, "answer": "\ud55c \ub9db\uc774 \ub098\ub2e4\n", "learned": false}, {"info1": "Ich schwimme jeden Tag einen Kilometer.", "info2": "", "date": "2018-12-29 21:09:25.181218", "chunk": 11, "question": "schwimmen ", "difficulty": 1, "answer": "\uc218\uc601\ud558\ub2e4\n", "learned": false}, {"info1": "Ich kann dich nicht sehen.", "info2": "", "date": "2018-12-29 21:09:25.181218", "chunk": 11, "question": "sehen ", "difficulty": 1, "answer": "\ubcf4\ub2e4\n", "learned": false}, {"info1": "Mir ist kalt.", "info2": "", "date": "2018-12-29 21:09:25.182225", "chunk": 11, "question": "sein", "difficulty": 1, "answer": "\uc774\ub2e4\n", "learned": false}, {"info1": "Das Licht ist noch an.", "info2": "", "date": "2018-12-29 21:09:25.182225", "chunk": 11, "question": "an sein", "difficulty": 1, "answer": "\ucf1c\uc788\ub2e4\n", "learned": false}, {"info1": "Herr Meier ist schon weg.", "info2": "", "date": "2018-12-29 21:09:25.182225", "chunk": 11, "question": "weg sein ", "difficulty": 1, "answer": "\uc5c6\ub2e4\n", "learned": false}, {"info1": "Die T\u00fcr ist zu.", "info2": "", "date": "2018-12-29 21:09:25.182225", "chunk": 11, "question": "zu sein", "difficulty": 1, "answer": "\ub2eb\ud600\uc788\ub2e4.\n", "learned": false}, {"info1": "Wo sitzen Sie?", "info2": "", "date": "2018-12-29 21:09:25.182225", "chunk": 11, "question": "sitzen ", "difficulty": 1, "answer": "\uc549\ub2e4\n", "learned": false}, {"info1": "Soll ich kommen?", "info2": "", "date": "2018-12-29 21:09:25.182225", "chunk": 11, "question": "sollen ", "difficulty": 1, "answer": "\u2219\u2219\u2219\ud574\uc57c \ud55c\ub2e4\n", "learned": false}, {"info1": "Die Kinder spielen drau\u00dfen.", "info2": "", "date": "2018-12-29 21:09:25.182225", "chunk": 12, "question": "spielen ", "difficulty": 1, "answer": "\ub180\uc774 \ud558\ub2e4\n", "learned": false}, {"info1": "Kann ich (mit) Herrn Klein sprechen?", "info2": "", "date": "2018-12-29 21:09:25.182225", "chunk": 12, "question": "sprechen ", "difficulty": 1, "answer": "\ub9d0\ud558\ub2e4, \uc774\uc57c\uae30\ud558\ub2e4\n", "learned": false}, {"info1": "Ich glaube es nicht, aber es steht in der Zeitung.", "info2": "", "date": "2018-12-29 21:09:25.182225", "chunk": 12, "question": "stehen ", "difficulty": 1, "answer": "\uc11c \uc788\ub2e4\n", "learned": false}, {"info1": "Stell die Tasche rechts in die Ecke!", "info2": "", "date": "2018-12-29 21:09:25.182225", "chunk": 12, "question": "stellen ", "difficulty": 1, "answer": "\uc138\uc6b0\ub2e4, (\uc138\uc6cc) \ub193\ub2e4\n", "learned": false}, {"info1": "Ich studiere in Mainz.", "info2": "", "date": "2018-12-29 21:09:25.182225", "chunk": 12, "question": "studieren ", "difficulty": 1, "answer": "\ubc30\uc6b0\ub2e4, \uacf5\ubd80\ud558\ub2e4, \ub300\ud559\uc5d0 \ub2e4\ub2c8\ub2e4\n", "learned": false}, {"info1": "Suchst du etwas?", "info2": "", "date": "2018-12-29 21:09:25.182225", "chunk": 12, "question": "suchen ", "difficulty": 1, "answer": "\ubb34\uc5c7\uc744 \ucc3e\ub2e4, \uad6c\ud558\ub2e4\n", "learned": false}, {"info1": "Tanzen Sie gern?", "info2": "", "date": "2018-12-29 21:09:25.182225", "chunk": 12, "question": "tanzen ", "difficulty": 1, "answer": "\ucda4\ucd94\ub2e4\n", "learned": false}, {"info1": "Darf ich mal telefonieren?", "info2": "", "date": "2018-12-29 21:09:25.182225", "chunk": 12, "question": "telefonieren ", "difficulty": 1, "answer": "\uc804\ud654 \ud1b5\ud654\ud558\ub2e4\n", "learned": false}, {"info1": "Ich treffe in der Stadt einen Kollegen.", "info2": "", "date": "2018-12-29 21:09:25.182225", "chunk": 12, "question": "(sich) treffen", "difficulty": 1, "answer": "\ub9cc\ub098\ub2e4\n", "learned": false}, {"info1": "M\u00f6chtest du etwas trinken?", "info2": "", "date": "2018-12-29 21:09:25.182225", "chunk": 12, "question": "trinken ", "difficulty": 1, "answer": "\ub9c8\uc2dc\ub2e4\n", "learned": false}, {"info1": "Ich habe noch etwas zu tun.", "info2": "", "date": "2018-12-29 21:09:25.182225", "chunk": 13, "question": "tun ", "difficulty": 1, "answer": "\ud558\ub2e4\n", "learned": false}, {"info1": "Du kannst bei mir \u00fcbernachten.", "info2": "", "date": "2018-12-29 21:09:25.182225", "chunk": 13, "question": "\u00fcbernachten ", "difficulty": 1, "answer": "\ubc24\uc744 \uc9c0\ub0b4\ub2e4, \ubb35\ub2e4, \uc219\ubc15\ud558\ub2e4\n", "learned": false}, {"info1": "Sie k\u00f6nnen das Geld auch \u00fcberweisen.", "info2": "", "date": "2018-12-29 21:09:25.182225", "chunk": 13, "question": "\u00fcberweisen ", "difficulty": 1, "answer": "\uc1a1\uae08\ud558\ub2e4, \uc785\uae08\ud558\ub2e4\n", "learned": false}, {"info1": "N\u00e4chsten Monat ziehen wir um.", "info2": "", "date": "2018-12-29 21:09:25.182225", "chunk": 13, "question": "umziehen ", "difficulty": 1, "answer": "\uc774\uc0ac \uac00\ub2e4\n", "learned": false}, {"info1": "Wo muss ich unterschreiben?", "info2": "", "date": "2018-12-29 21:09:25.182225", "chunk": 13, "question": "unterschreiben ", "difficulty": 1, "answer": "\u2219\u2219\u2219\uc5d0 \uc11c\uba85\ud558\ub2e4\n", "learned": false}, {"info1": "Ich verdiene 1.500 Euro im Monat.", "info2": "", "date": "2018-12-29 21:09:25.182225", "chunk": 13, "question": "verdienen ", "difficulty": 1, "answer": "(\uc77c\ud558\uc5ec) \uc5bb\ub2e4, \ubc8c\ub2e4\n", "learned": false}, {"info1": "Er verkauft sein altes Auto.", "info2": "", "date": "2018-12-29 21:09:25.182225", "chunk": 13, "question": "verkaufen ", "difficulty": 1, "answer": "\ud314\ub2e4, \ub9e4\uac01\ud558\ub2e4\n", "learned": false}, {"info1": "Die Wohnung ist schon vermietet.", "info2": "", "date": "2018-12-29 21:09:25.182225", "chunk": 13, "question": "vermieten ", "difficulty": 1, "answer": "(\ub3c8 \ubc1b\uace0) \ube4c\ub824\uc8fc\ub2e4, \uc784\ub300\ud558\ub2e4\n", "learned": false}, {"info1": "K\u00f6nnen Sie mich verstehen?", "info2": "", "date": "2018-12-29 21:09:25.182225", "chunk": 13, "question": "verstehen ", "difficulty": 1, "answer": "\ub4e3\ub2e4, \ub4e4\uc5b4\uc11c \uc54c\ub2e4\n", "learned": false}, {"info1": "Wir wollen uns kennenlernen. K\u00f6nnen Sie sich bitte vorstellen?", "info2": "", "date": "2018-12-29 21:09:25.182225", "chunk": 13, "question": "(sich) vorstellen", "difficulty": 1, "answer": "\uc790\uae30 \uc18c\uac1c\ub97c \ud558\ub2e4\n", "learned": false}, {"info1": "Wir wandern um den Chiemsee.", "info2": "", "date": "2018-12-29 21:09:25.182225", "chunk": 14, "question": "wandern ", "difficulty": 1, "answer": "\ud558\uc774\ud0b9 \ud558\ub2e4, \ub3c4\ubcf4 \uc5ec\ud589, \uc0b0\ucc45\ud558\ub2e4\n", "learned": false}, {"info1": "K\u00f6nnen Sie ein paar Minuten warten?", "info2": "", "date": "2018-12-29 21:09:25.182225", "chunk": 14, "question": "warten ", "difficulty": 1, "answer": "\uae30\ub2e4\ub9ac\ub2e4, \ub300\uae30\ud558\ub2e4\n", "learned": false}, {"info1": "Wo kann ich mir die H\u00e4nde waschen?", "info2": "", "date": "2018-12-29 21:09:25.182225", "chunk": 14, "question": "(sich) waschen", "difficulty": 1, "answer": "\uc53b\ub2e4\n", "learned": false}, {"info1": "Ich muss zum Arzt. Mein Bein tut weh.", "info2": "", "date": "2018-12-29 21:09:25.182225", "chunk": 14, "question": "weh tun ", "difficulty": 1, "answer": "\uc544\ud504\ub2e4\n", "learned": false}, {"info1": "Mein Sohn will Arzt werden.", "info2": "", "date": "2018-12-29 21:09:25.182225", "chunk": 14, "question": "werden ", "difficulty": 1, "answer": "\ub418\ub2e4\n", "learned": false}, {"info1": "K\u00f6nnen Sie das bitte wiederholen?", "info2": "", "date": "2018-12-29 21:09:25.182225", "chunk": 14, "question": "wiederholen ", "difficulty": 1, "answer": "\ub418\ud480\uc774\ud558\ub2e4, \ubc18\ubcf5\ud558\ub2e4\n", "learned": false}, {"info1": "Wei\u00dft du, wie er hei\u00dft?", "info2": "", "date": "2018-12-29 21:09:25.182225", "chunk": 14, "question": "wissen ", "difficulty": 1, "answer": "\uc54c\ub2e4, \uc54c\uace0 \uc788\ub2e4, \uc774\ud574\ud558\ub2e4\n", "learned": false}, {"info1": "Ich wohne in M\u00fcnchen.", "info2": "", "date": "2018-12-29 21:09:25.182225", "chunk": 14, "question": "wohnen ", "difficulty": 1, "answer": "\uc0b4\ub2e4, \uac70\uc8fc\ud558\ub2e4\n", "learned": false}, {"info1": "Wollen Sie einen Kaffee trinken?", "info2": "", "date": "2018-12-29 21:09:25.182225", "chunk": 14, "question": "wollen ", "difficulty": 1, "answer": "\uc6d0\ud558\ub2e4\n", "learned": false}, {"info1": "Zahlen, bitte!", "info2": "", "date": "2018-12-29 21:09:25.182225", "chunk": 14, "question": "zahlen ", "difficulty": 1, "answer": "(\ub3c8\uc744) \uce58\ub974\ub2e4, \uc9c0\uae09\ud558\ub2e4\n", "learned": false}]